juno_sdk/__init__.py
juno_sdk/client/__init__.py
juno_sdk/client/lcd/__init__.py
juno_sdk/client/lcd/api/__init__.py
juno_sdk/client/lcd/api/_base.py
juno_sdk/client/lcd/api/auth.py
juno_sdk/client/lcd/api/authz.py
juno_sdk/client/lcd/api/bank.py
juno_sdk/client/lcd/api/distribution.py
juno_sdk/client/lcd/api/feegrant.py
juno_sdk/client/lcd/api/gov.py
juno_sdk/client/lcd/api/ibc.py
juno_sdk/client/lcd/api/ibc_transfer.py
juno_sdk/client/lcd/api/mint.py
juno_sdk/client/lcd/api/slashing.py
juno_sdk/client/lcd/api/staking.py
juno_sdk/client/lcd/api/tendermint.py
juno_sdk/client/lcd/api/tx.py
juno_sdk/client/lcd/api/wasm.py
juno_sdk/client/lcd/lcdclient.py
juno_sdk/client/lcd/lcdutils.py
juno_sdk/client/lcd/params.py
juno_sdk/client/lcd/wallet.py
juno_sdk/client/localjuno.py
juno_sdk/core/__init__.py
juno_sdk/core/auth/__init__.py
juno_sdk/core/auth/data/__init__.py
juno_sdk/core/auth/data/account.py
juno_sdk/core/auth/data/base_account.py
juno_sdk/core/auth/data/base_vesting_account.py
juno_sdk/core/auth/data/continuous_vesting_account.py
juno_sdk/core/auth/data/delayed_vesting_account.py
juno_sdk/core/auth/data/periodic_vesting_account.py
juno_sdk/core/auth/msgs/__init__.py
juno_sdk/core/auth/msgs/msg_create_periodic_vesting_account.py
juno_sdk/core/auth/msgs/msg_create_vesting_account.py
juno_sdk/core/auth/msgs/msg_donate_all_vesting_tokens.py
juno_sdk/core/authz/__init__.py
juno_sdk/core/authz/data.py
juno_sdk/core/authz/msgs.py
juno_sdk/core/bank/__init__.py
juno_sdk/core/bank/msgs.py
juno_sdk/core/bech32.py
juno_sdk/core/block.py
juno_sdk/core/broadcast.py
juno_sdk/core/coin.py
juno_sdk/core/coins.py
juno_sdk/core/compact_bit_array.py
juno_sdk/core/crisis/__init__.py
juno_sdk/core/crisis/msgs.py
juno_sdk/core/deposit.py
juno_sdk/core/distribution/__init__.py
juno_sdk/core/distribution/msgs.py
juno_sdk/core/distribution/proposals.py
juno_sdk/core/fee.py
juno_sdk/core/feegrant/__init__.py
juno_sdk/core/feegrant/data.py
juno_sdk/core/feegrant/msgs.py
juno_sdk-0.0.1.dist-info/LICENSE
juno_sdk-0.0.1.dist-info/WHEEL
juno_sdk-0.0.1.dist-info/METADATA
juno_sdk-0.0.1.dist-info/RECORD
