Metadata-Version: 2.1
Name: juno-sdk
Version: 0.0.1
Summary: The Python SDK for Juno
Home-page: https://github.com/arufa-research/juno.py
License: MIT
Keywords: jigu,blockchain,juno,defi,crypto
Author: Terraform Labs, PTE.
Author-email: engineering@terra.money
Requires-Python: >=3.7,<4.0
Classifier: Intended Audience :: Developers
Classifier: License :: OSI Approved :: MIT License
Classifier: Natural Language :: English
Classifier: Programming Language :: Python :: 3
Classifier: Programming Language :: Python :: 3.10
Classifier: Programming Language :: Python :: 3.7
Classifier: Programming Language :: Python :: 3.8
Classifier: Programming Language :: Python :: 3.9
Requires-Dist: aiohttp (>=3.8.1,<4.0.0)
Requires-Dist: attrs (>=21.4.0,<22.0.0)
Requires-Dist: bech32 (>=1.2.0,<2.0.0)
Requires-Dist: betterproto (==2.0.0b4)
Requires-Dist: bip32utils (>=0.3.post4,<0.4)
Requires-Dist: boltons (>=21.0.0,<22.0.0)
Requires-Dist: ecdsa (>=0.17.0,<0.18.0)
Requires-Dist: furl (>=2.1.3,<3.0.0)
Requires-Dist: mnemonic (>=0.19,<0.20)
Requires-Dist: nest-asyncio (>=1.5.4,<2.0.0)
Requires-Dist: protobuf (>=3.19.1,<4.0.0)
Requires-Dist: terra-proto (==2.1.0)
Requires-Dist: wrapt (>=1.13.3,<2.0.0)
Project-URL: Documentation, https://arufaresearch.com/juno.py/index.html
Project-URL: Repository, https://github.com/arufa-research/juno.py
